<?xml version="1.0"?>
<!--<!DOCTYPE metadata SYSTEM "http://www.esri.com/metadata/esriprof80.dtd">-->
<metadata xml:lang="en"><Esri><CreaDate>20020207</CreaDate><CreaTime>13554200</CreaTime><SyncOnce>FALSE</SyncOnce><MetaID>{0E42DA64-8C10-4275-8434-0832D300E913}</MetaID><SyncDate>20020214</SyncDate><SyncTime>09133700</SyncTime><ModDate>20020214</ModDate><ModTime>09140700</ModTime><PublishedDocID>{81B0924E-2BDF-49DB-82AF-4FD2FD1BDBEE}</PublishedDocID></Esri><idinfo><citation><citeinfo><onlink>\exercise 5\image data\Topo.sid</onlink><origin>MassGIS, Commonwealth of Massachusetts Executive Office of Environmental Affairs.</origin><pubdate>Unknown</pubdate><title Sync="TRUE">Topo.sid</title><ftname Sync="TRUE">Topo.sid</ftname><geoform Sync="TRUE">remote-sensing image</geoform></citeinfo></citation><native Sync="TRUE">Microsoft Windows 2000 Version 5.0 (Build 2195) Service Pack 2; ESRI ArcCatalog 8.2.0.694</native><descript><langdata Sync="TRUE">en</langdata><abstract>An image created form a topographic map of the study area for the Animation tutorial.</abstract><purpose>To be used as a surface map for Exrecise 5 of the 3D  Analyst Tutorial.</purpose></descript><timeperd><current>publication date</current><timeinfo><sngdate><caldate>unknown</caldate></sngdate></timeinfo></timeperd><status><progress>Complete</progress><update>None planned</update></status><spdom><bounding><westbc Sync="TRUE">-72.894453</westbc><eastbc Sync="TRUE">-72.845186</eastbc><northbc Sync="TRUE">42.288601</northbc><southbc Sync="TRUE">42.252010</southbc></bounding><lboundng><leftbc Sync="TRUE">85000.000000</leftbc><rightbc Sync="TRUE">89000.606162</rightbc><bottombc Sync="TRUE">890000.000000</bottombc><topbc Sync="TRUE">894000.606162</topbc></lboundng></spdom><keywords><theme><themekey>topo</themekey></theme></keywords><accconst>None</accconst><useconst>See the ESRI License Agreement for Disclaimer of Warranties and Limitation on Liabilities with respect to the sample Data contained herein. The sample Data is the intellectual property of the respective data provider(s) and is used herein with permission. Source: MassGIS, Commonwealth of Massachusetts Executive Office of Environmental Affairs; ESRI. </useconst><natvform Sync="TRUE">Raster Dataset</natvform><datacred>Data courtesy of MassGIS, Commonwealth of Massachusetts Executive Office of Environmental Affairs.</datacred></idinfo><distInfo><distributor><distorTran><onLineSrc><linkage Sync="TRUE">file://\\TIN\D$\sourcesafe\books\3d analyst\potential tutorial\exercise 5\image data\Topo.sid</linkage><protocol Sync="TRUE">Local Area Network</protocol><orDesc Sync="TRUE">002</orDesc></onLineSrc><transSize Sync="TRUE">0.339</transSize></distorTran><distorFormat><formatName Sync="TRUE">Raster Dataset</formatName></distorFormat></distributor></distInfo><dataqual><lineage><procstep><procdesc Sync="TRUE">Dataset copied.</procdesc><srcused Sync="TRUE">d:\sourcesafe\books\3d analyst\potential tutorial\bratt\q89890.sid</srcused><date Sync="TRUE">20020207</date><time Sync="TRUE">13554200</time></procstep></lineage></dataqual><dataIdInfo><envirDesc Sync="TRUE">Microsoft Windows 2000 Version 5.0 (Build 2195) Service Pack 2; ESRI ArcCatalog 8.2.0.694</envirDesc><dataLang><languageCode Sync="TRUE" value="en"></languageCode></dataLang><idCitation><resTitle Sync="TRUE">Topo.sid</resTitle><presForm><PresFormCd Sync="TRUE" value="005"></PresFormCd></presForm></idCitation><spatRpType><SpatRepTypCd Sync="TRUE" value="002"></SpatRepTypCd></spatRpType><geoBox esriExtentType="native"><westBL Sync="TRUE">85000</westBL><eastBL Sync="TRUE">89000.606162</eastBL><northBL Sync="TRUE">894000.606162</northBL><southBL Sync="TRUE">890000</southBL><exTypeCode Sync="TRUE">1</exTypeCode></geoBox><geoBox esriExtentType="decdegrees"><westBL Sync="TRUE">-72.894453</westBL><eastBL Sync="TRUE">-72.845186</eastBL><northBL Sync="TRUE">42.288601</northBL><southBL Sync="TRUE">42.25201</southBL><exTypeCode Sync="TRUE">1</exTypeCode></geoBox></dataIdInfo><metainfo><langmeta Sync="TRUE">en</langmeta><metstdn Sync="TRUE">FGDC Content Standards for Digital Geospatial Metadata</metstdn><metstdv Sync="TRUE">FGDC-STD-001-1998</metstdv><mettc Sync="TRUE">local time</mettc><metc><cntinfo><cntorgp><cntper>ArcGIS Development Team</cntper><cntorg>Environmental Systems Research Institute, Inc. (ESRI)</cntorg></cntorgp><cntaddr><addrtype>mailing and physical address</addrtype><city>Redlands</city><state>California</state><postal>92373-8100</postal><address>380 New York St.</address><country>USA</country></cntaddr><cntvoice>909-793-2853</cntvoice><cnttdd>USA</cnttdd><cntfax>909-793-5953</cntfax><cntemail>info@esri.com</cntemail></cntinfo></metc><metd Sync="TRUE">20020214</metd><metextns><onlink Sync="TRUE">http://www.esri.com/metadata/esriprof80.html</onlink><metprof Sync="TRUE">ESRI Metadata Profile</metprof></metextns></metainfo><mdLang><languageCode Sync="TRUE" value="en"></languageCode></mdLang><mdStanName Sync="TRUE">ISO 19115 Geographic Information - Metadata</mdStanName><mdStanVer Sync="TRUE">DIS_ESRI1.0</mdStanVer><mdChar><CharSetCd Sync="TRUE" value="004"></CharSetCd></mdChar><mdHrLv><ScopeCd Sync="TRUE" value="005"></ScopeCd></mdHrLv><mdHrLvName Sync="TRUE">dataset</mdHrLvName><distinfo><resdesc Sync="TRUE">Downloadable Data</resdesc><stdorder><digform><digtinfo><transize Sync="TRUE">0.339</transize><dssize Sync="TRUE">0.339</dssize></digtinfo></digform></stdorder></distinfo><spdoinfo><direct Sync="TRUE">Raster</direct><rastinfo><rasttype Sync="TRUE">Pixel</rasttype><rowcount Sync="TRUE">1570</rowcount><colcount Sync="TRUE">1570</colcount><rastxsz Sync="TRUE">2.548157</rastxsz><rastysz Sync="TRUE">2.548157</rastysz><rastbpp Sync="TRUE">8</rastbpp><vrtcount Sync="TRUE">1</vrtcount><rastorig Sync="TRUE">Upper Left</rastorig><rastcmap Sync="TRUE">FALSE</rastcmap><rastcomp Sync="TRUE">Wavelet</rastcomp><rastband Sync="TRUE">3</rastband><rastdtyp Sync="TRUE">pixel codes</rastdtyp><rastplyr Sync="TRUE">TRUE</rastplyr><rastifor Sync="TRUE">MrSID</rastifor></rastinfo></spdoinfo><spatRepInfo><GridSpatRep><numDims Sync="TRUE">2</numDims><axDimProps><Dimen><dimName><DimNameTypCd Sync="TRUE" value="002"></DimNameTypCd></dimName><dimSize Sync="TRUE">1570</dimSize><dimResol Sync="TRUE">2.548157</dimResol></Dimen><Dimen><dimName><DimNameTypCd Sync="TRUE" value="001"></DimNameTypCd></dimName><dimSize Sync="TRUE">1570</dimSize><dimResol Sync="TRUE">2.548157</dimResol></Dimen></axDimProps><cellGeo><CellGeoCd Sync="TRUE" value="002"></CellGeoCd></cellGeo><tranParaAv Sync="TRUE">1</tranParaAv></GridSpatRep></spatRepInfo><spref><horizsys><planar><planci><plance Sync="TRUE">row and column</plance><coordrep><absres Sync="TRUE">2.548157</absres><ordres Sync="TRUE">2.548157</ordres></coordrep><plandu Sync="TRUE">meters</plandu></planci><gridsys><gridsysn>State Plane Coordinate System</gridsysn><spcs><spcszone Sync="TRUE">2001</spcszone><lambertc><stdparll Sync="TRUE">41.716667</stdparll><stdparll Sync="TRUE">42.683333</stdparll><longcm Sync="TRUE">-71.500000</longcm><latprjo Sync="TRUE">41.000000</latprjo><feast Sync="TRUE">200000.000000</feast><fnorth Sync="TRUE">750000.000000</fnorth></lambertc></spcs></gridsys></planar><cordsysn><geogcsn Sync="TRUE">GCS_North_American_1983</geogcsn><projcsn Sync="TRUE">NAD_1983_StatePlane_Massachusetts_Mainland_FIPS_2001</projcsn></cordsysn><geodetic><horizdn Sync="TRUE">North American Datum of 1983</horizdn><ellips Sync="TRUE">Geodetic Reference System 80</ellips><semiaxis Sync="TRUE">6378137.000000</semiaxis><denflat Sync="TRUE">298.257222</denflat></geodetic></horizsys><vertdef><altsys><altenc Sync="TRUE">Explicit elevation coordinate included with horizontal coordinates</altenc><altres Sync="TRUE">0.000000</altres></altsys></vertdef></spref><eainfo><detailed Name="Band_1"><enttyp><enttypl Sync="TRUE">Band_1</enttypl><enttypt Sync="TRUE">Table</enttypt><enttypc Sync="TRUE">256</enttypc></enttyp><attr><attrlabl Sync="TRUE">ObjectID</attrlabl><attalias Sync="TRUE">ObjectID</attalias><attrtype Sync="TRUE">OID</attrtype><attwidth Sync="TRUE">4</attwidth><atprecis Sync="TRUE">0</atprecis><attscale Sync="TRUE">0</attscale><attrdef Sync="TRUE">Internal feature number.</attrdef><attrdefs Sync="TRUE">ESRI</attrdefs><attrdomv><udom Sync="TRUE">Sequential unique whole numbers that are automatically generated.</udom></attrdomv></attr><attr><attrlabl Sync="TRUE">Value</attrlabl><attalias Sync="TRUE">Value</attalias><attrtype Sync="TRUE">Integer</attrtype><attwidth Sync="TRUE">0</attwidth><atprecis Sync="TRUE">0</atprecis><attscale Sync="TRUE">0</attscale></attr><attr><attrlabl Sync="TRUE">Count</attrlabl><attalias Sync="TRUE">Count</attalias><attrtype Sync="TRUE">Integer</attrtype><attwidth Sync="TRUE">0</attwidth><atprecis Sync="TRUE">0</atprecis><attscale Sync="TRUE">0</attscale></attr></detailed><detailed Name="Band_2"><enttyp><enttypl Sync="TRUE">Band_2</enttypl><enttypt Sync="TRUE">Table</enttypt><enttypc Sync="TRUE">256</enttypc></enttyp><attr><attrlabl Sync="TRUE">ObjectID</attrlabl><attalias Sync="TRUE">ObjectID</attalias><attrtype Sync="TRUE">OID</attrtype><attwidth Sync="TRUE">4</attwidth><atprecis Sync="TRUE">0</atprecis><attscale Sync="TRUE">0</attscale><attrdef Sync="TRUE">Internal feature number.</attrdef><attrdefs Sync="TRUE">ESRI</attrdefs><attrdomv><udom Sync="TRUE">Sequential unique whole numbers that are automatically generated.</udom></attrdomv></attr><attr><attrlabl Sync="TRUE">Value</attrlabl><attalias Sync="TRUE">Value</attalias><attrtype Sync="TRUE">Integer</attrtype><attwidth Sync="TRUE">0</attwidth><atprecis Sync="TRUE">0</atprecis><attscale Sync="TRUE">0</attscale></attr><attr><attrlabl Sync="TRUE">Count</attrlabl><attalias Sync="TRUE">Count</attalias><attrtype Sync="TRUE">Integer</attrtype><attwidth Sync="TRUE">0</attwidth><atprecis Sync="TRUE">0</atprecis><attscale Sync="TRUE">0</attscale></attr></detailed><detailed Name="Band_3"><enttyp><enttypl Sync="TRUE">Band_3</enttypl><enttypt Sync="TRUE">Table</enttypt><enttypc Sync="TRUE">256</enttypc></enttyp><attr><attrlabl Sync="TRUE">ObjectID</attrlabl><attalias Sync="TRUE">ObjectID</attalias><attrtype Sync="TRUE">OID</attrtype><attwidth Sync="TRUE">4</attwidth><atprecis Sync="TRUE">0</atprecis><attscale Sync="TRUE">0</attscale><attrdef Sync="TRUE">Internal feature number.</attrdef><attrdefs Sync="TRUE">ESRI</attrdefs><attrdomv><udom Sync="TRUE">Sequential unique whole numbers that are automatically generated.</udom></attrdomv></attr><attr><attrlabl Sync="TRUE">Value</attrlabl><attalias Sync="TRUE">Value</attalias><attrtype Sync="TRUE">Integer</attrtype><attwidth Sync="TRUE">0</attwidth><atprecis Sync="TRUE">0</atprecis><attscale Sync="TRUE">0</attscale></attr><attr><attrlabl Sync="TRUE">Count</attrlabl><attalias Sync="TRUE">Count</attalias><attrtype Sync="TRUE">Integer</attrtype><attwidth Sync="TRUE">0</attwidth><atprecis Sync="TRUE">0</atprecis><attscale Sync="TRUE">0</attscale></attr></detailed></eainfo><mdDateSt Sync="TRUE">20020214</mdDateSt><refSysInfo><RefSystem><refSysID><identCode Sync="TRUE">NAD_1983_StatePlane_Massachusetts_Mainland_FIPS_2001</identCode></refSysID></RefSystem></refSysInfo></metadata>
